Dockerfile
captain-definition
docker-compose.yml
formative/__init__.py
formative/admin/__init__.py
formative/admin/actions.py
formative/admin/formative.py
formative/apps.py
formative/backends.py
formative/filetype/__init__.py
formative/filetype/av.py
formative/filetype/document.py
formative/filetype/image.py
formative/forms/__init__.py
formative/forms/admin.py
formative/forms/formative.py
formative/middleware.py
formative/migrations/0001_initial.py
formative/migrations/0002_initial.py
formative/migrations/0003_submissionrecord_and_more.py
formative/migrations/0004_alter_form_db_slug_alter_form_slug_and_more.py
formative/migrations/0005_alter_formblock__rank.py
formative/migrations/0006_alter_formblock__rank.py
formative/migrations/0007_alter_collectionblock_align_type.py
formative/migrations/0008_site_program_sites.py
formative/migrations/0009_custom_user_model.py
formative/migrations/0010_alter_user_options_user_site_user_uniq_site_email_and_more.py
formative/migrations/__init__.py
formative/models/__init__.py
formative/models/automatic.py
formative/models/formative.py
formative/models/ranked.py
formative/models/site.py
formative/plugins.py
formative/signals.py
formative/stock/__init__.py
formative/stock/address.py
formative/stock/choiceset.py
formative/stock/date.py
formative/stock/email.py
formative/stock/name.py
formative/stock/phone.py
formative/stock/url.py
formative/tasks.py
formative/templatetags/__init__.py
formative/templatetags/form_block.py
formative/templatetags/form_signal.py
formative/templatetags/patched_widget_tweaks.py
formative/templatetags/program.py
formative/templatetags/utils.py
formative/urls.py
formative/utils.py
formative/validators.py
formative/views.py
manage.py
settings.py
urls.py
formative-0.9.10.dist-info/LICENSE
formative-0.9.10.dist-info/WHEEL
formative-0.9.10.dist-info/METADATA
formative-0.9.10.dist-info/RECORD
